fastax/__init__.py
fastax/utils.py
fastax/activations/__init__.py
fastax/activations/activations.py
fastax/layers/__init__.py
fastax/layers/attention.py
fastax/layers/attention_test.py
fastax/layers/base.py
fastax/layers/base_test.py
fastax/layers/combinators.py
fastax/layers/combinators_test.py
fastax/layers/convolution.py
fastax/layers/convolution_test.py
fastax/layers/core.py
fastax/layers/core_test.py
fastax/layers/initializers.py
fastax/layers/initializers_test.py
fastax/layers/normalization.py
fastax/layers/normalization_test.py
fastax/layers/pooling.py
fastax/layers/pooling_test.py
fastax/layers/reversible.py
fastax/layers/reversible_test.py
fastax/layers/rnn.py
fastax/layers/rnn_test.py
fastax/losses/__init__.py
fastax/losses/losses.py
fastax/optimizers/__init__.py
fastax/optimizers/base.py
fastax/optimizers/optimizers.py
fastax-0.1.3.dist-info/METADATA
fastax-0.1.3.dist-info/WHEEL
fastax-0.1.3.dist-info/top_level.txt
fastax-0.1.3.dist-info/RECORD
