Metadata-Version: 2.1
Name: fastax
Version: 0.1.3
Summary: A Jax based neural network library for research
Home-page: https://github.com/joaogui1/fastax
Author: João Guilherme Madeira Araújo
Author-email: joaoguilhermearujo@gmail.com
License: Apache-2.0
Platform: UNKNOWN
Classifier: License :: OSI Approved :: Apache Software License
Classifier: Programming Language :: Python :: 3
Classifier: Programming Language :: Python :: 3.7
Requires-Dist: jax
Requires-Dist: jaxlib
Requires-Dist: numpy
